doq/__init__.py
doq/_shtab.py
doq/cli.py
doq/config.py
doq/outputter.py
doq/parser.py
doq/template.py
doq/templates/google/class.txt
doq/templates/google/def.txt
doq/templates/google/noarg.txt
doq/templates/numpy/class.txt
doq/templates/numpy/def.txt
doq/templates/numpy/noarg.txt
doq/templates/sphinx/class.txt
doq/templates/sphinx/def.txt
doq/templates/sphinx/noarg.txt
doq-0.10.0.data/data/share/bash-completion/completions/doq
doq-0.10.0.data/data/share/man/man1/doq.1
doq-0.10.0.data/data/share/zsh/site-functions/_doq
doq-0.10.0.dist-info/LICENSE
doq-0.10.0.dist-info/METADATA
doq-0.10.0.dist-info/WHEEL
doq-0.10.0.dist-info/entry_points.txt
doq-0.10.0.dist-info/top_level.txt
doq-0.10.0.dist-info/RECORD
