Metadata-Version: 2.1
Name: doq
Version: 0.10.0
Summary: Docstring generator
Author-email: Shinya Ohyanagi <sohyanagi@gmail.com>
License: BSD
Project-URL: Homepage, http://github.com/heavenshell/py-doq
Classifier: Development Status :: 4 - Beta
Classifier: Environment :: Web Environment
Classifier: Intended Audience :: Developers
Classifier: License :: OSI Approved :: BSD License
Classifier: Operating System :: OS Independent
Classifier: Programming Language :: Python
Classifier: Topic :: Documentation
Classifier: Topic :: Software Development :: Documentation
License-File: LICENSE
Requires-Dist: parso
Requires-Dist: jinja2
Requires-Dist: toml
Provides-Extra: completion
Requires-Dist: shtab ; extra == 'completion'
Provides-Extra: test
Requires-Dist: parameterized ; extra == 'test'
Requires-Dist: pytest ; extra == 'test'
